{"name":"Simple-browser","tagline":"Simple browser UI for wireframes and mockups —for Illustrator (& Sketch coming soon…)","body":"Simple-browser\r\n==============\r\n\r\nSimple browser UI for wireframes and mockups —for Illustrator (&amp; Sketch coming soon…)\r\n\r\n# What is it?\r\n\r\nSimple browser files contain graphic elements that you can use to put your wireframes or mockups in the context of a web browser.\r\n\r\n# 3 Styles\r\n\r\nThe browser elements come in 3 differents style:\r\n\r\n* A — Neutral (quite mainstream to be honest)\r\n* B — Smooth (closer to Chrome or Firefox flavour)\r\n* C — Ghost (skeleton lines)\r\n\r\nHere is a preview of those 3 style\r\n\r\n**Style A - Neutral** \r\n![Style A - Neutral](img/preview-A.png)\r\n\r\n**Style B - Smooth**\r\n![Style B - Smooth](img/preview-B.png)\r\n\r\n**Style C - Ghost**\r\n![Style C - Ghost](img/preview-C.png)\r\n\r\n# Illustrator file\r\n\r\nThe Adobe Illustrator CC file contains the 3 styles.\r\nThe 6 artboards are regrouping:\r\n\r\n* The graphic elements as source **vector shapes**\r\n* The browser style as **symbols objects** (that you can resize to fit your mockups width)\r\n* The color palette with global color (that you can tweak to adapt to your own visual design)\r\n\r\nThis file is composed of **3 layers**:\r\n\r\n* Instructions (where you will find some extra information on how to use the elements)\r\n* Elements (the sources elements and the symbols as well as the guides)\r\n* Background (the dark blue color at the back)\r\n\r\n# The Sketch file (coming soon…)\r\n\r\nThis file will contain hopefully the same content as the Illustrator one! Stay tuned…\r\n\r\n---\r\n\r\nLast edition: Dec. 5th 2014","google":"","note":"Don't delete this file! It's used internally to help with page regeneration."}